README.md
setup.py
lift/__init__.py
lift/coloring.py
lift/console.py
lift.bot.egg-info/PKG-INFO
lift.bot.egg-info/SOURCES.txt
lift.bot.egg-info/dependency_links.txt
lift.bot.egg-info/requires.txt
lift.bot.egg-info/top_level.txt