Metadata-Version: 2.1
Name: lift.bot
Version: 21.0.1
Summary: lift.bot
Home-page: https://github.com/bytebuildz/liftcord.py-tools/
Author: .drmr
Author-email: hi@icey.fr
License: MIT License
Keywords: lift
Classifier: Programming Language :: Python
Classifier: Programming Language :: Python :: 2
Classifier: Programming Language :: Python :: 2.7
Classifier: Programming Language :: Python :: 3
Classifier: Programming Language :: Python :: 3.5
Classifier: Programming Language :: Python :: 3.6
Classifier: Programming Language :: Python :: 3.7
Classifier: Programming Language :: Python :: 3.8
Classifier: Programming Language :: Python :: 3.9
Classifier: Programming Language :: Python :: 3.10
